{
   "tag": "div",
   "conteudoTextual": null,
   "conteudo": [
      {
         "tag": "h1",
         "conteudoTextual": "Títul top das galáxia",
         "conteudo": [],
         "atributos": {
            "id": "titulo_principal",
            "class": "titulo"
         },
         "style": {
            "color": "red",
            "font-weight": "bold",
            "font-size": "15px"
         }
      },
      {
         "tag": "p",
         "conteudoTextual": "Conteúdo gerado para teste",
         "conteudo": [],
         "atributos": {
            "id": "p_principal",
            "class": "paragrafo"
         },
         "style": {
            "color": "red",
            "font-weight": "bold",
            "font-size": "15px"
         }
      }
   ],
   "atributos": {
      "id": "container",
      "class": "box"
   },
   "style": {
      "margin": "4px",
      "color": "red",
      "margin-color": "black",
      "font-size": "14px"
   }
}